setup.py
bin/easyban
easyban/__init__.py
easyban.egg-info/PKG-INFO
easyban.egg-info/SOURCES.txt
easyban.egg-info/dependency_links.txt
easyban.egg-info/requires.txt
easyban.egg-info/top_level.txt